brachy/__init__.py
brachy/functional.py
brachy/nn.py
brachy/optional_module.py
brachy/rng_util.py
brachy/optim/__init__.py
brachy/optim/adamw.py
brachy/optim/mixed_precision.py
brachy/optim/process_grads.py
brachy/optim/random_scaling.py
brachy/optim/schedules.py
brachy/optim/sgd.py
brachy/structure_util/__init__.py
brachy/structure_util/checkpoint.py
brachy/structure_util/static_wrapper.py
brachy/structure_util/structure_util_core.py
brachy-0.0.2.dist-info/METADATA
brachy-0.0.2.dist-info/WHEEL
brachy-0.0.2.dist-info/RECORD
