Metadata-Version: 2.1
Name: brachy
Version: 0.0.2
Summary: pytorch-like ML with Jax
Project-URL: Documentation, https://github.com/optimizedlearning/brachy#readme
Project-URL: Issues, https://github.com/unknown/optimizedlearning/issues
Project-URL: Source, https://github.com/optimizedlearning/brachy
Author-email: Ashok Cutkosky <ashok@cutkosky.com>
License-Expression: MIT
Classifier: Development Status :: 4 - Beta
Classifier: Programming Language :: Python
Classifier: Programming Language :: Python :: 3.7
Classifier: Programming Language :: Python :: 3.8
Classifier: Programming Language :: Python :: 3.9
Classifier: Programming Language :: Python :: 3.10
Classifier: Programming Language :: Python :: 3.11
Classifier: Programming Language :: Python :: Implementation :: CPython
Classifier: Programming Language :: Python :: Implementation :: PyPy
Requires-Python: >=3.7
Requires-Dist: dill
Requires-Dist: einops
